cloud_tasks_deferred/__init__.py
cloud_tasks_deferred/__version__.py
cloud_tasks_deferred/deferred.py
cloud_tasks_deferred/wsgi.py
cloud_tasks_deferred-0.1.0.dist-info/LICENSE
cloud_tasks_deferred-0.1.0.dist-info/METADATA
cloud_tasks_deferred-0.1.0.dist-info/WHEEL
cloud_tasks_deferred-0.1.0.dist-info/top_level.txt
cloud_tasks_deferred-0.1.0.dist-info/RECORD
