Metadata-Version: 2.1
Name: cloud-tasks-deferred
Version: 0.1.0
Summary: A deferred library for Google Cloud Tasks
Home-page: https://github.com/grktsh/python-cloud-tasks-deferred
License: UNKNOWN
Platform: UNKNOWN
Classifier: Development Status :: 3 - Alpha
Classifier: Intended Audience :: Developers
Classifier: License :: OSI Approved :: Apache Software License
Classifier: Programming Language :: Python :: 2
Classifier: Programming Language :: Python :: 2.7
Classifier: Programming Language :: Python :: 3
Classifier: Programming Language :: Python :: 3.7
Classifier: Programming Language :: Python :: 3.8
Requires-Dist: google-cloud-tasks (~=1.3)
Provides-Extra: test
Requires-Dist: pytest (<6,>=4.4) ; extra == 'test'
Requires-Dist: pytest-cov (~=2.6) ; extra == 'test'
Requires-Dist: pytest-mock (~=1.10) ; extra == 'test'
Requires-Dist: pytest-xdist (~=1.28) ; extra == 'test'
Requires-Dist: falcon (~=2.0) ; extra == 'test'
